pymoto/__init__.py
pymoto/core_objects.py
pymoto/routines.py
pymoto/utils.py
pymoto/common/domain.py
pymoto/common/dyadcarrier.py
pymoto/common/mma.py
pymoto/modules/aggregation.py
pymoto/modules/assembly.py
pymoto/modules/autodiff.py
pymoto/modules/complex.py
pymoto/modules/filter.py
pymoto/modules/generic.py
pymoto/modules/io.py
pymoto/modules/linalg.py
pymoto/modules/scaling.py
pymoto/solvers/__init__.py
pymoto/solvers/auto_determine.py
pymoto/solvers/dense.py
pymoto/solvers/iterative.py
pymoto/solvers/matrix_checks.py
pymoto/solvers/solvers.py
pymoto/solvers/sparse.py
pyMOTO-1.5.0.dist-info/LICENSE
pyMOTO-1.5.0.dist-info/METADATA
pyMOTO-1.5.0.dist-info/WHEEL
pyMOTO-1.5.0.dist-info/top_level.txt
pyMOTO-1.5.0.dist-info/zip-safe
pyMOTO-1.5.0.dist-info/RECORD
