Metadata-Version: 2.1
Name: pyMOTO
Version: 1.5.0
Summary: A modular approach for topology optimization
Home-page: https://github.com/aatmdelissen/pyMOTO
Author: Arnoud Delissen
Author-email: arnouddelissen+pymoto@gmail.com
License: MIT License
Keywords: topology optimization,generative design,structural,sensitivities,derivatives,framework,modular,blocks,pipeline
Classifier: Programming Language :: Python :: 3
Classifier: Operating System :: OS Independent
Classifier: License :: OSI Approved :: MIT License
Classifier: Topic :: Scientific/Engineering
License-File: LICENSE
Requires-Dist: numpy
Requires-Dist: scipy >=1.7
Requires-Dist: sympy
Requires-Dist: matplotlib
Provides-Extra: dev
Requires-Dist: flake8 ; extra == 'dev'
Requires-Dist: pytest ; extra == 'dev'
Requires-Dist: cvxopt ; extra == 'dev'
Requires-Dist: scikit-sparse ; extra == 'dev'
Requires-Dist: pypardiso ; extra == 'dev'
Requires-Dist: jax[cpu] ; extra == 'dev'
